app.py
generate_parquet.py
server.py
tools/csv_tools.py
tools/parquet_tools.py
utils/file_reader.py
summarize_csv_file-0.1.4.dist-info/METADATA
summarize_csv_file-0.1.4.dist-info/WHEEL
summarize_csv_file-0.1.4.dist-info/entry_points.txt
summarize_csv_file-0.1.4.dist-info/top_level.txt
summarize_csv_file-0.1.4.dist-info/RECORD
