Metadata-Version: 2.4
Name: summarize-csv-file
Version: 0.1.4
Summary: Summarize the CSV file
Author-email: sadasiba <sadasiba@gmail.com>
License: MIT
Requires-Python: >=3.9
Requires-Dist: mcp[cli]>=1.12.4
Requires-Dist: pandas>=2.3.1
Requires-Dist: pyarrow>=21.0.0
